CHANGELOG.md
LICENSE
README.rst
flake8_custom_import_rules/__init__.py
flake8_custom_import_rules/__main__.py
flake8_custom_import_rules/codes/__init__.py
flake8_custom_import_rules/codes/error_codes.py
flake8_custom_import_rules/codes/exceptions.py
flake8_custom_import_rules/core/__init__.py
flake8_custom_import_rules/core/enums.py
flake8_custom_import_rules/core/error_messages.py
flake8_custom_import_rules/core/import_rules.py
flake8_custom_import_rules/core/node_visitor.py
flake8_custom_import_rules/core/nodes.py
flake8_custom_import_rules/core/restricted_import_visitor.py
flake8_custom_import_rules/core/rules_checker.py
flake8_custom_import_rules/defaults.py
flake8_custom_import_rules/flake8_plugin.py
flake8_custom_import_rules/utils/__init__.py
flake8_custom_import_rules/utils/file_utils.py
flake8_custom_import_rules/utils/node_utils.py
flake8_custom_import_rules/utils/option_utils.py
flake8_custom_import_rules/utils/parse_utils.py
flake8_custom_import_rules/utils/restricted_import_utils.py
flake8_custom_import_rules-1.1.6.dist-info/LICENSE
flake8_custom_import_rules-1.1.6.dist-info/METADATA
flake8_custom_import_rules-1.1.6.dist-info/WHEEL
flake8_custom_import_rules-1.1.6.dist-info/entry_points.txt
flake8_custom_import_rules-1.1.6.dist-info/RECORD
