Metadata-Version: 2.1
Name: flake8_custom_import_rules
Version: 1.1.6
Summary: A Flake8 plugin that enforces custom import rules, allowing users to define and maintain clean and consistent import organization across their Python projects.
Home-page: https://github.com/RodrigoGonzalez/flake8-custom-import-rules
License: MIT
Keywords: code_quality,code_linting,import_rules,flake8,quality_assurance
Author: Rodrigo Gonzalez
Author-email: flake8.custom.import.rules@gmail.com
Requires-Python: >=3.9,<4
Classifier: Development Status :: 4 - Beta
Classifier: Environment :: Console
Classifier: Framework :: Flake8
Classifier: Intended Audience :: Developers
Classifier: License :: OSI Approved :: MIT License
Classifier: Operating System :: OS Independent
Classifier: Programming Language :: Python :: 3
Classifier: Programming Language :: Python :: 3.9
Classifier: Programming Language :: Python :: 3.10
Classifier: Programming Language :: Python :: 3.11
Classifier: Programming Language :: Python :: 3.12
Classifier: Programming Language :: Python :: 3.13
Classifier: Programming Language :: Python :: 3 :: Only
Classifier: Topic :: Software Development :: Libraries :: Python Modules
Classifier: Topic :: Software Development :: Quality Assurance
Classifier: Typing :: Typed
Requires-Dist: attrs (>=24.3.0,<25.0.0)
Requires-Dist: flake8 (>=6.1,<8.0)
Requires-Dist: importlib-metadata ; python_version < "3.8"
Requires-Dist: pycodestyle (>=2.11.1,<3.0.0)
Requires-Dist: pylama (>=8.4.1,<9.0.0)
Requires-Dist: pymdown-extensions (>=10.7,<11.0)
Requires-Dist: stdlib-list (>=0.10.0) ; python_version < "3.10"
Requires-Dist: typer (>=0.15.1,<0.16.0)
Project-URL: Change Log, https://github.com/RodrigoGonzalez/flake8-custom-import-rules/blob/main/CHANGELOG.md
Project-URL: Documentation, https://RodrigoGonzalez.github.io/flake8-custom-import-rules/
Project-URL: GitHub, https://github.com/RodrigoGonzalez/flake8-custom-import-rules
Project-URL: Repository, https://github.com/RodrigoGonzalez/flake8-custom-import-rules
